ENCRYPTION_DECRYTION/__init__.py
Encryption_decryption-2.1.dist-info/LICENSE.txt
Encryption_decryption-2.1.dist-info/METADATA
Encryption_decryption-2.1.dist-info/WHEEL
Encryption_decryption-2.1.dist-info/top_level.txt
Encryption_decryption-2.1.dist-info/RECORD
